streamlit_tldraw/__init__.py
streamlit_tldraw/example.py
streamlit_tldraw-0.1.1.dist-info/licenses/LICENSE
streamlit_tldraw-0.1.1.dist-info/METADATA
streamlit_tldraw-0.1.1.dist-info/WHEEL
streamlit_tldraw-0.1.1.dist-info/top_level.txt
streamlit_tldraw-0.1.1.dist-info/RECORD
